octool/__init__.py
octool/__main__.py
octool/cli.py
octool/version.py
octool-0.0.11.dist-info/LICENSE
octool-0.0.11.dist-info/METADATA
octool-0.0.11.dist-info/WHEEL
octool-0.0.11.dist-info/entry_points.txt
octool-0.0.11.dist-info/top_level.txt
octool-0.0.11.dist-info/RECORD
