Metadata-Version: 2.1
Name: octool
Version: 0.0.11
Summary: Open Compliance Tool
Home-page: https://github.com/jumanjihouse/octool
Author: Paul Morgan
Author-email: jumanjiman@gmail.com
License: GPLv3+
Keywords: compliance documentation
Platform: UNKNOWN
Classifier: Development Status :: 3 - Alpha
Classifier: Topic :: Utilities
Classifier: Intended Audience :: End Users/Desktop
Classifier: Environment :: Console
Classifier: License :: OSI Approved :: GNU General Public License v3 or later (GPLv3+)
Classifier: Programming Language :: Python :: 3
Classifier: Programming Language :: Python :: 3.5
Classifier: Programming Language :: Python :: 3.6
Classifier: Programming Language :: Python :: 3.7
Classifier: Programming Language :: Python :: 3.8
Classifier: Programming Language :: Python :: 3 :: Only
Requires-Python: >=3.5, <4
